{
   "asset" : {
      "generator" : "osg2cesiumApp",
      "version" : "1.0"
   },
   "root" : {
      "boundingVolume" : {
         "box" : [
            -132.81253051757812,
            237.92166137695312,
            -116.65022277832031,
            7.8907394409179688,
            0.0,
            0.0,
            0.0,
            3.6250228881835938,
            0.0,
            0.0,
            0.0,
            4.0138664245605469
         ]
      },
      "children" : [
         {
            "boundingVolume" : {
               "box" : [
                  -136.71881103515625,
                  236.35903930664062,
                  -116.90023803710938,
                  3.9453659057617188,
                  0.0,
                  0.0,
                  0.0,
                  2.0233535766601562,
                  0.0,
                  0.0,
                  0.0,
                  3.7355308532714844
               ]
            },
            "content" : {
               "uri" : "h1103330.json"
            },
            "geometricError" : 0.64876502752304077
         },
         {
            "boundingVolume" : {
               "box" : [
                  -128.90621948242188,
                  237.93331909179688,
                  -117.07368469238281,
                  3.9453697204589844,
                  0.0,
                  0.0,
                  0.0,
                  3.5976181030273438,
                  0.0,
                  0.0,
                  0.0,
                  3.5951118469238281
               ]
            },
            "content" : {
               "uri" : "h1103331.json"
            },
            "geometricError" : 0.64876502752304077
         },
         {
            "boundingVolume" : {
               "box" : [
                  -138.39131164550781,
                  235.22381591796875,
                  -112.93959045410156,
                  0.3138885498046875,
                  0.0,
                  0.0,
                  0.0,
                  0.8880615234375,
                  0.0,
                  0.0,
                  0.0,
                  0.3032684326171875
               ]
            },
            "content" : {
               "uri" : "h1103332.json"
            },
            "geometricError" : 0.64876502752304077
         }
      ],
      "content" : {
         "uri" : "g110333.b3dm"
      },
      "geometricError" : 1.2975300550460815
   }
}
