{
   "asset" : {
      "generator" : "osg2cesiumApp",
      "version" : "1.0"
   },
   "root" : {
      "boundingVolume" : {
         "box" : [
            -54.686538696289062,
            195.31179809570312,
            -116.43971252441406,
            7.8907489776611328,
            0.0,
            0.0,
            0.0,
            7.8907394409179688,
            0.0,
            0.0,
            0.0,
            3.41790771484375
         ]
      },
      "children" : [
         {
            "boundingVolume" : {
               "box" : [
                  -58.59283447265625,
                  191.40548706054688,
                  -118.62046051025391,
                  3.9453716278076172,
                  0.0,
                  0.0,
                  0.0,
                  3.9453887939453125,
                  0.0,
                  0.0,
                  0.0,
                  1.093780517578125
               ]
            },
            "content" : {
               "uri" : "h1113000.json"
            },
            "geometricError" : 0.64876693487167358
         },
         {
            "boundingVolume" : {
               "box" : [
                  -50.780235290527344,
                  191.40548706054688,
                  -119.57044982910156,
                  3.9453716278076172,
                  0.0,
                  0.0,
                  0.0,
                  3.9453811645507812,
                  0.0,
                  0.0,
                  0.0,
                  0.15976715087890625
               ]
            },
            "content" : {
               "uri" : "h1113001.json"
            },
            "geometricError" : 0.64876693487167358
         },
         {
            "boundingVolume" : {
               "box" : [
                  -58.59283447265625,
                  199.21809387207031,
                  -118.55635070800781,
                  3.9453907012939453,
                  0.0,
                  0.0,
                  0.0,
                  3.9453887939453125,
                  0.0,
                  0.0,
                  0.0,
                  1.3012657165527344
               ]
            },
            "content" : {
               "uri" : "h1113002.json"
            },
            "geometricError" : 0.64876693487167358
         },
         {
            "boundingVolume" : {
               "box" : [
                  -50.780235290527344,
                  199.21807861328125,
                  -116.44717407226562,
                  3.9453964233398438,
                  0.0,
                  0.0,
                  0.0,
                  3.945404052734375,
                  0.0,
                  0.0,
                  0.0,
                  3.2830467224121094
               ]
            },
            "content" : {
               "uri" : "h1113003.json"
            },
            "geometricError" : 0.64876693487167358
         },
         {
            "boundingVolume" : {
               "box" : [
                  -52.002265930175781,
                  199.96109008789062,
                  -113.13167572021484,
                  0.50490379333496094,
                  0.0,
                  0.0,
                  0.0,
                  0.52777099609375,
                  0.0,
                  0.0,
                  0.0,
                  0.11060333251953125
               ]
            },
            "content" : {
               "uri" : "h1113004.json"
            },
            "geometricError" : 0.64876693487167358
         }
      ],
      "content" : {
         "uri" : "g111300.b3dm"
      },
      "geometricError" : 1.2975338697433472
   }
}
