{
   "asset" : {
      "generator" : "osg2cesiumApp",
      "version" : "1.0"
   },
   "root" : {
      "boundingVolume" : {
         "box" : [
            -39.061416625976562,
            148.43626403808594,
            -112.42848205566406,
            7.8908309936523438,
            0.0,
            0.0,
            0.0,
            7.890838623046875,
            0.0,
            0.0,
            0.0,
            7.118194580078125
         ]
      },
      "children" : [
         {
            "boundingVolume" : {
               "box" : [
                  -42.967681884765625,
                  144.5299072265625,
                  -116.35488891601562,
                  3.9454250335693359,
                  0.0,
                  0.0,
                  0.0,
                  3.9454269409179688,
                  0.0,
                  0.0,
                  0.0,
                  3.1914634704589844
               ]
            },
            "content" : {
               "uri" : "h1111030.json"
            },
            "geometricError" : 0.64876741170883179
         },
         {
            "boundingVolume" : {
               "box" : [
                  -35.155082702636719,
                  144.5299072265625,
                  -116.71454620361328,
                  3.9454212188720703,
                  0.0,
                  0.0,
                  0.0,
                  3.945404052734375,
                  0.0,
                  0.0,
                  0.0,
                  2.8217849731445312
               ]
            },
            "content" : {
               "uri" : "h1111031.json"
            },
            "geometricError" : 0.64876741170883179
         },
         {
            "boundingVolume" : {
               "box" : [
                  -42.507293701171875,
                  149.470458984375,
                  -115.45478057861328,
                  3.4850254058837891,
                  0.0,
                  0.0,
                  0.0,
                  1.0733413696289062,
                  0.0,
                  0.0,
                  0.0,
                  2.2914047241210938
               ]
            },
            "content" : {
               "uri" : "h1111032.json"
            },
            "geometricError" : 0.64876741170883179
         },
         {
            "boundingVolume" : {
               "box" : [
                  -35.155071258544922,
                  149.96087646484375,
                  -116.09205627441406,
                  3.9454154968261719,
                  0.0,
                  0.0,
                  0.0,
                  1.56378173828125,
                  0.0,
                  0.0,
                  0.0,
                  2.9287757873535156
               ]
            },
            "content" : {
               "uri" : "h1111033.json"
            },
            "geometricError" : 0.64876741170883179
         },
         {
            "boundingVolume" : {
               "box" : [
                  -44.387920379638672,
                  147.99281311035156,
                  -109.2955322265625,
                  2.5252723693847656,
                  0.0,
                  0.0,
                  0.0,
                  0.4826507568359375,
                  0.0,
                  0.0,
                  0.0,
                  3.9460563659667969
               ]
            },
            "content" : {
               "uri" : "h1111034.json"
            },
            "geometricError" : 0.64876741170883179
         },
         {
            "boundingVolume" : {
               "box" : [
                  -42.967761993408203,
                  152.34262084960938,
                  -109.2955322265625,
                  3.9454307556152344,
                  0.0,
                  0.0,
                  0.0,
                  3.9454269409179688,
                  0.0,
                  0.0,
                  0.0,
                  3.9460563659667969
               ]
            },
            "content" : {
               "uri" : "h1111035.json"
            },
            "geometricError" : 0.64876741170883179
         },
         {
            "boundingVolume" : {
               "box" : [
                  -35.155158996582031,
                  152.641357421875,
                  -109.29544067382812,
                  3.9454011917114258,
                  0.0,
                  0.0,
                  0.0,
                  3.6466903686523438,
                  0.0,
                  0.0,
                  0.0,
                  3.9460868835449219
               ]
            },
            "content" : {
               "uri" : "h1111036.json"
            },
            "geometricError" : 0.64876741170883179
         }
      ],
      "content" : {
         "uri" : "g111103.b3dm"
      },
      "geometricError" : 1.2975348234176636
   }
}
