{
   "asset" : {
      "generator" : "osg2cesiumApp",
      "version" : "1.0"
   },
   "root" : {
      "boundingVolume" : {
         "box" : [
            -191.40696716308594,
            176.92538452148438,
            -112.41359710693359,
            3.94537353515625,
            0.0,
            0.0,
            0.0,
            2.8003768920898438,
            0.0,
            0.0,
            0.0,
            0.8285675048828125
         ]
      },
      "content" : {
         "uri" : "h1100335.b3dm"
      },
      "geometricError" : 0.64876347780227661
   }
}
