{
   "asset" : {
      "generator" : "osg2cesiumApp",
      "version" : "1.0"
   },
   "root" : {
      "boundingVolume" : {
         "box" : [
            -238.28257751464844,
            167.96775817871094,
            -116.71331787109375,
            3.9454345703125,
            0.0,
            0.0,
            0.0,
            3.9454193115234375,
            0.0,
            0.0,
            0.0,
            3.5502052307128906
         ]
      },
      "content" : {
         "uri" : "h1100203.b3dm"
      },
      "geometricError" : 0.6487622857093811
   }
}
