{
   "asset" : {
      "generator" : "osg2cesiumApp",
      "version" : "1.0"
   },
   "root" : {
      "boundingVolume" : {
         "box" : [
            93.749671936035156,
            93.7510986328125,
            -106.61636352539062,
            31.562936782836914,
            0.0,
            0.0,
            0.0,
            31.563014984130859,
            0.0,
            0.0,
            0.0,
            12.853294372558594
         ]
      },
      "children" : [
         {
            "boundingVolume" : {
               "box" : [
                  78.124519348144531,
                  78.125885009765625,
                  -108.59703826904297,
                  15.781534194946289,
                  0.0,
                  0.0,
                  0.0,
                  15.781551361083984,
                  0.0,
                  0.0,
                  0.0,
                  10.836090087890625
               ]
            },
            "content" : {
               "uri" : "f21230.json"
            },
            "geometricError" : 5.1901531219482422
         },
         {
            "boundingVolume" : {
               "box" : [
                  109.37486267089844,
                  78.12591552734375,
                  -108.56889343261719,
                  15.781490325927734,
                  0.0,
                  0.0,
                  0.0,
                  15.78154182434082,
                  0.0,
                  0.0,
                  0.0,
                  10.830429077148438
               ]
            },
            "content" : {
               "uri" : "f21231.json"
            },
            "geometricError" : 5.190159797668457
         },
         {
            "boundingVolume" : {
               "box" : [
                  78.124504089355469,
                  109.37612915039062,
                  -108.66274261474609,
                  15.781526565551758,
                  0.0,
                  0.0,
                  0.0,
                  15.78131103515625,
                  0.0,
                  0.0,
                  0.0,
                  10.830291748046875
               ]
            },
            "content" : {
               "uri" : "f21232.json"
            },
            "geometricError" : 5.1901531219482422
         },
         {
            "boundingVolume" : {
               "box" : [
                  109.37485504150391,
                  109.37624359130859,
                  -106.58460998535156,
                  15.781494140625,
                  0.0,
                  0.0,
                  0.0,
                  15.7816162109375,
                  0.0,
                  0.0,
                  0.0,
                  12.821544647216797
               ]
            },
            "content" : {
               "uri" : "f21233.json"
            },
            "geometricError" : 5.190159797668457
         }
      ],
      "content" : {
         "uri" : "e2123.b3dm"
      },
      "geometricError" : 20.760618209838867
   }
}
