{
   "asset" : {
      "generator" : "osg2cesiumApp",
      "version" : "1.0"
   },
   "root" : {
      "boundingVolume" : {
         "box" : [
            354.60791015625,
            -102.099365234375,
            -119.85403442382812,
            11.01458740234375,
            0.0,
            0.0,
            0.0,
            8.50445556640625,
            0.0,
            0.0,
            0.0,
            0.66290283203125
         ]
      },
      "children" : [
         {
            "boundingVolume" : {
               "box" : [
                  345.252197265625,
                  -109.935302734375,
                  -119.79039764404297,
                  1.580718994140625,
                  0.0,
                  0.0,
                  0.0,
                  0.63705825805664062,
                  0.0,
                  0.0,
                  0.0,
                  0.09995269775390625
               ]
            },
            "content" : {
               "uri" : "g230110.json"
            },
            "geometricError" : 1.2975502014160156
         },
         {
            "boundingVolume" : {
               "box" : [
                  351.56219482421875,
                  -101.56378173828125,
                  -119.93975067138672,
                  7.8907623291015625,
                  0.0,
                  0.0,
                  0.0,
                  7.8907356262207031,
                  0.0,
                  0.0,
                  0.0,
                  0.57422637939453125
               ]
            },
            "content" : {
               "uri" : "g230111.json"
            },
            "geometricError" : 1.2975502014160156
         },
         {
            "boundingVolume" : {
               "box" : [
                  362.4595947265625,
                  -98.974166870117188,
                  -119.51655578613281,
                  3.1629180908203125,
                  0.0,
                  0.0,
                  0.0,
                  5.3011207580566406,
                  0.0,
                  0.0,
                  0.0,
                  0.32542800903320312
               ]
            },
            "content" : {
               "uri" : "g230112.json"
            },
            "geometricError" : 1.2975510358810425
         }
      ],
      "content" : {
         "uri" : "f23011.b3dm"
      },
      "geometricError" : 5.1902012825012207
   }
}
