{
   "asset" : {
      "generator" : "osg2cesiumApp",
      "version" : "1.0"
   },
   "root" : {
      "boundingVolume" : {
         "box" : [
            85.937118530273438,
            34.824996948242188,
            -113.18058013916016,
            7.8907890319824219,
            0.0,
            0.0,
            0.0,
            3.6527414321899414,
            0.0,
            0.0,
            0.0,
            6.1995620727539062
         ]
      },
      "children" : [
         {
            "boundingVolume" : {
               "box" : [
                  82.030792236328125,
                  34.073673248291016,
                  -117.09440612792969,
                  3.9454116821289062,
                  0.0,
                  0.0,
                  0.0,
                  2.8623628616333008,
                  0.0,
                  0.0,
                  0.0,
                  2.2603988647460938
               ]
            },
            "content" : {
               "uri" : "h2121210.json"
            },
            "geometricError" : 0.64876943826675415
         },
         {
            "boundingVolume" : {
               "box" : [
                  89.8433837890625,
                  34.837917327880859,
                  -117.11153411865234,
                  3.9454078674316406,
                  0.0,
                  0.0,
                  0.0,
                  3.6266069412231445,
                  0.0,
                  0.0,
                  0.0,
                  2.2774810791015625
               ]
            },
            "content" : {
               "uri" : "h2121211.json"
            },
            "geometricError" : 0.64876943826675415
         },
         {
            "boundingVolume" : {
               "box" : [
                  82.030830383300781,
                  35.567657470703125,
                  -110.96614074707031,
                  3.9454116821289062,
                  0.0,
                  0.0,
                  0.0,
                  1.68280029296875,
                  0.0,
                  0.0,
                  0.0,
                  3.9460563659667969
               ]
            },
            "content" : {
               "uri" : "h2121212.json"
            },
            "geometricError" : 0.64876943826675415
         },
         {
            "boundingVolume" : {
               "box" : [
                  89.843429565429688,
                  36.896537780761719,
                  -110.9661865234375,
                  3.9454078674316406,
                  0.0,
                  0.0,
                  0.0,
                  1.5027141571044922,
                  0.0,
                  0.0,
                  0.0,
                  3.9460487365722656
               ]
            },
            "content" : {
               "uri" : "h2121213.json"
            },
            "geometricError" : 0.64876943826675415
         }
      ],
      "content" : {
         "uri" : "g212121.b3dm"
      },
      "geometricError" : 1.2975388765335083
   }
}
