{
   "asset" : {
      "generator" : "osg2cesiumApp",
      "version" : "1.0"
   },
   "root" : {
      "boundingVolume" : {
         "box" : [
            226.56385803222656,
            54.688213348388672,
            -117.18009948730469,
            7.8907928466796875,
            0.0,
            0.0,
            0.0,
            7.8907699584960938,
            0.0,
            0.0,
            0.0,
            3.3553390502929688
         ]
      },
      "children" : [
         {
            "boundingVolume" : {
               "box" : [
                  222.6575927734375,
                  50.781913757324219,
                  -118.619873046875,
                  3.9454193115234375,
                  0.0,
                  0.0,
                  0.0,
                  3.945404052734375,
                  0.0,
                  0.0,
                  0.0,
                  1.6234550476074219
               ]
            },
            "content" : {
               "uri" : "h2131320.json"
            },
            "geometricError" : 0.64877301454544067
         },
         {
            "boundingVolume" : {
               "box" : [
                  230.47018432617188,
                  50.781917572021484,
                  -119.85285949707031,
                  3.9454116821289062,
                  0.0,
                  0.0,
                  0.0,
                  3.9453849792480469,
                  0.0,
                  0.0,
                  0.0,
                  0.68477249145507812
               ]
            },
            "content" : {
               "uri" : "h2131321.json"
            },
            "geometricError" : 0.64877301454544067
         },
         {
            "boundingVolume" : {
               "box" : [
                  222.65756225585938,
                  58.594512939453125,
                  -118.62319946289062,
                  3.9454116821289062,
                  0.0,
                  0.0,
                  0.0,
                  3.9454135894775391,
                  0.0,
                  0.0,
                  0.0,
                  1.6577110290527344
               ]
            },
            "content" : {
               "uri" : "h2131322.json"
            },
            "geometricError" : 0.64877301454544067
         },
         {
            "boundingVolume" : {
               "box" : [
                  230.47019958496094,
                  58.594520568847656,
                  -120.23696899414062,
                  3.9453887939453125,
                  0.0,
                  0.0,
                  0.0,
                  3.9454059600830078,
                  0.0,
                  0.0,
                  0.0,
                  0.26371383666992188
               ]
            },
            "content" : {
               "uri" : "h2131323.json"
            },
            "geometricError" : 0.64877301454544067
         },
         {
            "boundingVolume" : {
               "box" : [
                  233.2415771484375,
                  49.052597045898438,
                  -114.01065063476562,
                  0.18045806884765625,
                  0.0,
                  0.0,
                  0.0,
                  0.18469047546386719,
                  0.0,
                  0.0,
                  0.0,
                  0.18589019775390625
               ]
            },
            "content" : {
               "uri" : "h2131324.json"
            },
            "geometricError" : 0.64877301454544067
         }
      ],
      "content" : {
         "uri" : "g213132.b3dm"
      },
      "geometricError" : 1.2975460290908813
   }
}
