{
   "asset" : {
      "generator" : "osg2cesiumApp",
      "version" : "1.0"
   },
   "root" : {
      "boundingVolume" : {
         "box" : [
            289.06143188476562,
            -39.06298828125,
            -121.01397705078125,
            7.8907470703125,
            0.0,
            0.0,
            0.0,
            7.8907489776611328,
            0.0,
            0.0,
            0.0,
            0.10482025146484375
         ]
      },
      "children" : [
         {
            "boundingVolume" : {
               "box" : [
                  285.15512084960938,
                  -42.969291687011719,
                  -121.01587677001953,
                  3.94537353515625,
                  0.0,
                  0.0,
                  0.0,
                  3.9453887939453125,
                  0.0,
                  0.0,
                  0.0,
                  0.07997894287109375
               ]
            },
            "content" : {
               "uri" : "h2302120.json"
            },
            "geometricError" : 0.64877355098724365
         },
         {
            "boundingVolume" : {
               "box" : [
                  292.96771240234375,
                  -42.96929931640625,
                  -121.05096435546875,
                  3.9454193115234375,
                  0.0,
                  0.0,
                  0.0,
                  3.9453754425048828,
                  0.0,
                  0.0,
                  0.0,
                  0.06783294677734375
               ]
            },
            "content" : {
               "uri" : "h2302121.json"
            },
            "geometricError" : 0.64877355098724365
         },
         {
            "boundingVolume" : {
               "box" : [
                  285.1551513671875,
                  -35.156684875488281,
                  -120.98061370849609,
                  3.9454193115234375,
                  0.0,
                  0.0,
                  0.0,
                  3.9453887939453125,
                  0.0,
                  0.0,
                  0.0,
                  0.07962799072265625
               ]
            },
            "content" : {
               "uri" : "h2302122.json"
            },
            "geometricError" : 0.64877355098724365
         },
         {
            "boundingVolume" : {
               "box" : [
                  292.96774291992188,
                  -35.156681060791016,
                  -121.00780487060547,
                  3.94537353515625,
                  0.0,
                  0.0,
                  0.0,
                  3.9453897476196289,
                  0.0,
                  0.0,
                  0.0,
                  0.053009033203125
               ]
            },
            "content" : {
               "uri" : "h2302123.json"
            },
            "geometricError" : 0.64877355098724365
         }
      ],
      "content" : {
         "uri" : "g230212.b3dm"
      },
      "geometricError" : 1.2975471019744873
   }
}
