{
   "asset" : {
      "generator" : "osg2cesiumApp",
      "version" : "1.0"
   },
   "root" : {
      "boundingVolume" : {
         "box" : [
            273.436279296875,
            7.8126010894775391,
            -119.44306945800781,
            7.8907928466796875,
            0.0,
            0.0,
            0.0,
            7.8907585144042969,
            0.0,
            0.0,
            0.0,
            1.5373458862304688
         ]
      },
      "children" : [
         {
            "boundingVolume" : {
               "box" : [
                  269.52993774414062,
                  3.906301736831665,
                  -120.86557006835938,
                  3.945404052734375,
                  0.0,
                  0.0,
                  0.0,
                  3.9453756809234619,
                  0.0,
                  0.0,
                  0.0,
                  0.11484909057617188
               ]
            },
            "content" : {
               "uri" : "h2310010.json"
            },
            "geometricError" : 0.64877307415008545
         },
         {
            "boundingVolume" : {
               "box" : [
                  277.34255981445312,
                  3.9063074588775635,
                  -120.8096923828125,
                  3.94537353515625,
                  0.0,
                  0.0,
                  0.0,
                  3.9453747272491455,
                  0.0,
                  0.0,
                  0.0,
                  0.15378952026367188
               ]
            },
            "content" : {
               "uri" : "h2310011.json"
            },
            "geometricError" : 0.64877307415008545
         },
         {
            "boundingVolume" : {
               "box" : [
                  269.52993774414062,
                  11.718908309936523,
                  -120.86258697509766,
                  3.945404052734375,
                  0.0,
                  0.0,
                  0.0,
                  3.9453775882720947,
                  0.0,
                  0.0,
                  0.0,
                  0.07814788818359375
               ]
            },
            "content" : {
               "uri" : "h2310012.json"
            },
            "geometricError" : 0.64877307415008545
         },
         {
            "boundingVolume" : {
               "box" : [
                  277.34255981445312,
                  11.718902587890625,
                  -119.46986389160156,
                  3.945404052734375,
                  0.0,
                  0.0,
                  0.0,
                  3.9453907012939453,
                  0.0,
                  0.0,
                  0.0,
                  1.5056037902832031
               ]
            },
            "content" : {
               "uri" : "h2310013.json"
            },
            "geometricError" : 0.64877307415008545
         }
      ],
      "content" : {
         "uri" : "g231001.b3dm"
      },
      "geometricError" : 1.2975461483001709
   }
}
