{
   "asset" : {
      "generator" : "osg2cesiumApp",
      "version" : "1.0"
   },
   "root" : {
      "boundingVolume" : {
         "box" : [
            11.717426300048828,
            -58.594451904296875,
            -117.11709594726562,
            3.9454100131988525,
            0.0,
            0.0,
            0.0,
            3.9453945159912109,
            0.0,
            0.0,
            0.0,
            2.2840690612792969
         ]
      },
      "content" : {
         "uri" : "h2102001.b3dm"
      },
      "geometricError" : 0.64876741170883179
   }
}
