{
   "asset" : {
      "generator" : "osg2cesiumApp",
      "version" : "1.0"
   },
   "root" : {
      "boundingVolume" : {
         "box" : [
            124.10086059570312,
            27.344091415405273,
            -117.08335113525391,
            0.9383087158203125,
            0.0,
            0.0,
            0.0,
            3.9453887939453125,
            0.0,
            0.0,
            0.0,
            2.2491531372070312
         ]
      },
      "content" : {
         "uri" : "h2121133.b3dm"
      },
      "geometricError" : 0.64877021312713623
   }
}
