{
   "asset" : {
      "generator" : "osg2cesiumApp",
      "version" : "1.0"
   },
   "root" : {
      "boundingVolume" : {
         "box" : [
            105.46862030029297,
            6.0716462135314941,
            -102.83036804199219,
            3.9453964233398438,
            0.0,
            0.0,
            0.0,
            1.7800283432006836,
            0.0,
            0.0,
            0.0,
            3.6239814758300781
         ]
      },
      "content" : {
         "uri" : "h2121141.b3dm"
      },
      "geometricError" : 0.6487697958946228
   }
}
