{
   "asset" : {
      "generator" : "osg2cesiumApp",
      "version" : "1.0"
   },
   "root" : {
      "boundingVolume" : {
         "box" : [
            316.405517578125,
            3.9063074588775635,
            -120.88101196289062,
            3.9453887939453125,
            0.0,
            0.0,
            0.0,
            3.945387601852417,
            0.0,
            0.0,
            0.0,
            0.32825088500976562
         ]
      },
      "content" : {
         "uri" : "h2311000.b3dm"
      },
      "geometricError" : 0.64877426624298096
   }
}
