{
   "asset" : {
      "generator" : "osg2cesiumApp",
      "version" : "1.0"
   },
   "root" : {
      "boundingVolume" : {
         "box" : [
            218.18898010253906,
            218.74957275390625,
            -119.78561401367188,
            31.000640869140625,
            0.0,
            0.0,
            0.0,
            31.562950134277344,
            0.0,
            0.0,
            0.0,
            0.93392562866210938
         ]
      },
      "children" : [
         {
            "boundingVolume" : {
               "box" : [
                  203.1260986328125,
                  203.1243896484375,
                  -119.83956146240234,
                  15.781517028808594,
                  0.0,
                  0.0,
                  0.0,
                  15.781494140625,
                  0.0,
                  0.0,
                  0.0,
                  0.7308502197265625
               ]
            },
            "content" : {
               "uri" : "f30130.json"
            },
            "geometricError" : 5.1901788711547852
         },
         {
            "boundingVolume" : {
               "box" : [
                  233.86083984375,
                  203.12437438964844,
                  -119.98382568359375,
                  15.265861511230469,
                  0.0,
                  0.0,
                  0.0,
                  15.781494140625,
                  0.0,
                  0.0,
                  0.0,
                  0.74606704711914062
               ]
            },
            "content" : {
               "uri" : "f30131.json"
            },
            "geometricError" : 5.190185546875
         },
         {
            "boundingVolume" : {
               "box" : [
                  203.1260986328125,
                  234.37478637695312,
                  -119.81516265869141,
                  15.781494140625,
                  0.0,
                  0.0,
                  0.0,
                  15.781494140625,
                  0.0,
                  0.0,
                  0.0,
                  0.7552490234375
               ]
            },
            "content" : {
               "uri" : "f30132.json"
            },
            "geometricError" : 5.1901788711547852
         },
         {
            "boundingVolume" : {
               "box" : [
                  227.56376647949219,
                  234.37478637695312,
                  -119.57264709472656,
                  8.96875,
                  0.0,
                  0.0,
                  0.0,
                  15.781478881835938,
                  0.0,
                  0.0,
                  0.0,
                  0.31914901733398438
               ]
            },
            "content" : {
               "uri" : "f30133.json"
            },
            "geometricError" : 5.190185546875
         }
      ],
      "content" : {
         "uri" : "e3013.b3dm"
      },
      "geometricError" : 20.760721206665039
   }
}
