{
   "asset" : {
      "generator" : "osg2cesiumApp",
      "version" : "1.0"
   },
   "root" : {
      "boundingVolume" : {
         "box" : [
            93.749679565429688,
            327.290283203125,
            -115.15826416015625,
            31.562934875488281,
            0.0,
            0.0,
            0.0,
            15.102066040039062,
            0.0,
            0.0,
            0.0,
            5.1109237670898438
         ]
      },
      "children" : [
         {
            "boundingVolume" : {
               "box" : [
                  78.124496459960938,
                  321.03985595703125,
                  -115.15260314941406,
                  15.781496047973633,
                  0.0,
                  0.0,
                  0.0,
                  8.6954193115234375,
                  0.0,
                  0.0,
                  0.0,
                  5.1979217529296875
               ]
            },
            "content" : {
               "uri" : "f30230.json"
            },
            "geometricError" : 5.1901531219482422
         },
         {
            "boundingVolume" : {
               "box" : [
                  109.3748779296875,
                  327.33697509765625,
                  -115.98516845703125,
                  15.781490325927734,
                  0.0,
                  0.0,
                  0.0,
                  14.992446899414062,
                  0.0,
                  0.0,
                  0.0,
                  4.1669120788574219
               ]
            },
            "content" : {
               "uri" : "f30231.json"
            },
            "geometricError" : 5.190159797668457
         }
      ],
      "content" : {
         "uri" : "e3023.b3dm"
      },
      "geometricError" : 20.760618209838867
   }
}
