{
   "asset" : {
      "generator" : "osg2cesiumApp",
      "version" : "1.0"
   },
   "root" : {
      "boundingVolume" : {
         "box" : [
            118.35588073730469,
            143.78599548339844,
            -96.538619995117188,
            6.7223434448242188,
            0.0,
            0.0,
            0.0,
            3.240142822265625,
            0.0,
            0.0,
            0.0,
            1.529876708984375
         ]
      },
      "children" : [
         {
            "boundingVolume" : {
               "box" : [
                  114.43006896972656,
                  143.03533935546875,
                  -96.720169067382812,
                  2.7965278625488281,
                  0.0,
                  0.0,
                  0.0,
                  2.4504165649414062,
                  0.0,
                  0.0,
                  0.0,
                  1.3092384338378906
               ]
            },
            "content" : {
               "uri" : "h3001520.json"
            },
            "geometricError" : 0.64877021312713623
         },
         {
            "boundingVolume" : {
               "box" : [
                  121.09378051757812,
                  143.80081176757812,
                  -96.523895263671875,
                  3.9453849792480469,
                  0.0,
                  0.0,
                  0.0,
                  3.2158660888671875,
                  0.0,
                  0.0,
                  0.0,
                  1.5055274963378906
               ]
            },
            "content" : {
               "uri" : "h3001521.json"
            },
            "geometricError" : 0.64877021312713623
         }
      ],
      "content" : {
         "uri" : "g300152.b3dm"
      },
      "geometricError" : 1.2975404262542725
   }
}
