{
   "asset" : {
      "generator" : "osg2cesiumApp",
      "version" : "1.0"
   },
   "root" : {
      "boundingVolume" : {
         "box" : [
            70.732040405273438,
            229.23086547851562,
            -112.34284973144531,
            7.4706592559814453,
            0.0,
            0.0,
            0.0,
            5.2221221923828125,
            0.0,
            0.0,
            0.0,
            1.3541069030761719
         ]
      },
      "children" : [
         {
            "boundingVolume" : {
               "box" : [
                  72.322280883789062,
                  224.533203125,
                  -113.48068237304688,
                  0.39929580688476562,
                  0.0,
                  0.0,
                  0.0,
                  0.54299163818359375,
                  0.0,
                  0.0,
                  0.0,
                  0.17718124389648438
               ]
            },
            "content" : {
               "uri" : "h3003240.json"
            },
            "geometricError" : 0.64876925945281982
         },
         {
            "boundingVolume" : {
               "box" : [
                  66.814628601074219,
                  233.0133056640625,
                  -112.31773376464844,
                  3.5363979339599609,
                  0.0,
                  0.0,
                  0.0,
                  1.4006118774414062,
                  0.0,
                  0.0,
                  0.0,
                  1.3401336669921875
               ]
            },
            "content" : {
               "uri" : "h3003241.json"
            },
            "geometricError" : 0.64876925945281982
         },
         {
            "boundingVolume" : {
               "box" : [
                  74.218246459960938,
                  233.37811279296875,
                  -112.37165832519531,
                  3.9453887939453125,
                  0.0,
                  0.0,
                  0.0,
                  1.035797119140625,
                  0.0,
                  0.0,
                  0.0,
                  1.2862319946289062
               ]
            },
            "content" : {
               "uri" : "h3003242.json"
            },
            "geometricError" : 0.64876925945281982
         }
      ],
      "content" : {
         "uri" : "g300324.b3dm"
      },
      "geometricError" : 1.2975385189056396
   }
}
