{
   "asset" : {
      "generator" : "osg2cesiumApp",
      "version" : "1.0"
   },
   "root" : {
      "boundingVolume" : {
         "box" : [
            66.405593872070312,
            159.26177978515625,
            -116.51190185546875,
            3.9454116821289062,
            0.0,
            0.0,
            0.0,
            3.0520401000976562,
            0.0,
            0.0,
            0.0,
            2.9329109191894531
         ]
      },
      "content" : {
         "uri" : "h3001200.b3dm"
      },
      "geometricError" : 0.6487690806388855
   }
}
