{
   "asset" : {
      "generator" : "osg2cesiumApp",
      "version" : "1.0"
   },
   "root" : {
      "boundingVolume" : {
         "box" : [
            -289.061279296875,
            -195.311767578125,
            -122.31296539306641,
            7.8907470703125,
            0.0,
            0.0,
            0.0,
            7.8907470703125,
            0.0,
            0.0,
            0.0,
            0.685821533203125
         ]
      },
      "children" : [
         {
            "boundingVolume" : {
               "box" : [
                  -292.96759033203125,
                  -199.21806335449219,
                  -122.66658020019531,
                  3.945404052734375,
                  0.0,
                  0.0,
                  0.0,
                  3.9453887939453125,
                  0.0,
                  0.0,
                  0.0,
                  0.21103668212890625
               ]
            },
            "content" : {
               "uri" : "h0021230.json"
            },
            "geometricError" : 0.64876216650009155
         },
         {
            "boundingVolume" : {
               "box" : [
                  -285.15496826171875,
                  -199.21806335449219,
                  -122.80184936523438,
                  3.9453887939453125,
                  0.0,
                  0.0,
                  0.0,
                  3.9453887939453125,
                  0.0,
                  0.0,
                  0.0,
                  0.19694137573242188
               ]
            },
            "content" : {
               "uri" : "h0021231.json"
            },
            "geometricError" : 0.64876216650009155
         },
         {
            "boundingVolume" : {
               "box" : [
                  -292.96759033203125,
                  -191.40545654296875,
                  -122.34658813476562,
                  3.945404052734375,
                  0.0,
                  0.0,
                  0.0,
                  3.9453887939453125,
                  0.0,
                  0.0,
                  0.0,
                  0.45878219604492188
               ]
            },
            "content" : {
               "uri" : "h0021232.json"
            },
            "geometricError" : 0.64876216650009155
         },
         {
            "boundingVolume" : {
               "box" : [
                  -285.15496826171875,
                  -191.40545654296875,
                  -122.18406677246094,
                  3.9453887939453125,
                  0.0,
                  0.0,
                  0.0,
                  3.9453887939453125,
                  0.0,
                  0.0,
                  0.0,
                  0.54457473754882812
               ]
            },
            "content" : {
               "uri" : "h0021233.json"
            },
            "geometricError" : 0.64876216650009155
         }
      ],
      "content" : {
         "uri" : "g002123.b3dm"
      },
      "geometricError" : 1.2975243330001831
   }
}
