{
   "asset" : {
      "generator" : "osg2cesiumApp",
      "version" : "1.0"
   },
   "root" : {
      "boundingVolume" : {
         "box" : [
            -320.31173706054688,
            -39.062980651855469,
            -116.00406646728516,
            7.8907470703125,
            0.0,
            0.0,
            0.0,
            7.8907556533813477,
            0.0,
            0.0,
            0.0,
            3.4822845458984375
         ]
      },
      "children" : [
         {
            "boundingVolume" : {
               "box" : [
                  -324.21807861328125,
                  -42.969276428222656,
                  -116.70840454101562,
                  3.9453887939453125,
                  0.0,
                  0.0,
                  0.0,
                  3.9453983306884766,
                  0.0,
                  0.0,
                  0.0,
                  2.7246589660644531
               ]
            },
            "content" : {
               "uri" : "h0112130.json"
            },
            "geometricError" : 0.64876145124435425
         },
         {
            "boundingVolume" : {
               "box" : [
                  -316.40545654296875,
                  -42.969276428222656,
                  -116.01502990722656,
                  3.945404052734375,
                  0.0,
                  0.0,
                  0.0,
                  3.9453849792480469,
                  0.0,
                  0.0,
                  0.0,
                  2.031280517578125
               ]
            },
            "content" : {
               "uri" : "h0112131.json"
            },
            "geometricError" : 0.64876145124435425
         },
         {
            "boundingVolume" : {
               "box" : [
                  -324.21804809570312,
                  -35.156681060791016,
                  -116.73506164550781,
                  3.94537353515625,
                  0.0,
                  0.0,
                  0.0,
                  3.9453926086425781,
                  0.0,
                  0.0,
                  0.0,
                  2.7512855529785156
               ]
            },
            "content" : {
               "uri" : "h0112132.json"
            },
            "geometricError" : 0.64876145124435425
         },
         {
            "boundingVolume" : {
               "box" : [
                  -316.40545654296875,
                  -35.156669616699219,
                  -115.68795013427734,
                  3.945404052734375,
                  0.0,
                  0.0,
                  0.0,
                  3.9453926086425781,
                  0.0,
                  0.0,
                  0.0,
                  1.7041854858398438
               ]
            },
            "content" : {
               "uri" : "h0112133.json"
            },
            "geometricError" : 0.64876145124435425
         },
         {
            "boundingVolume" : {
               "box" : [
                  -323.25503540039062,
                  -42.893417358398438,
                  -113.27644348144531,
                  2.98236083984375,
                  0.0,
                  0.0,
                  0.0,
                  3.8695411682128906,
                  0.0,
                  0.0,
                  0.0,
                  0.78551864624023438
               ]
            },
            "content" : {
               "uri" : "h0112134.json"
            },
            "geometricError" : 0.64876145124435425
         },
         {
            "boundingVolume" : {
               "box" : [
                  -319.5552978515625,
                  -40.8575439453125,
                  -113.48904418945312,
                  0.795562744140625,
                  0.0,
                  0.0,
                  0.0,
                  1.8336639404296875,
                  0.0,
                  0.0,
                  0.0,
                  0.57287979125976562
               ]
            },
            "content" : {
               "uri" : "h0112135.json"
            },
            "geometricError" : 0.64876145124435425
         },
         {
            "boundingVolume" : {
               "box" : [
                  -322.21270751953125,
                  -35.536922454833984,
                  -113.50812530517578,
                  1.9400177001953125,
                  0.0,
                  0.0,
                  0.0,
                  3.565093994140625,
                  0.0,
                  0.0,
                  0.0,
                  0.553863525390625
               ]
            },
            "content" : {
               "uri" : "h0112136.json"
            },
            "geometricError" : 0.64876145124435425
         },
         {
            "boundingVolume" : {
               "box" : [
                  -318.26806640625,
                  -35.156665802001953,
                  -113.52500152587891,
                  2.0828094482421875,
                  0.0,
                  0.0,
                  0.0,
                  3.9453811645507812,
                  0.0,
                  0.0,
                  0.0,
                  0.53696441650390625
               ]
            },
            "content" : {
               "uri" : "h0112137.json"
            },
            "geometricError" : 0.64876145124435425
         }
      ],
      "content" : {
         "uri" : "g011213.b3dm"
      },
      "geometricError" : 1.2975229024887085
   }
}
