{
   "asset" : {
      "generator" : "osg2cesiumApp",
      "version" : "1.0"
   },
   "root" : {
      "boundingVolume" : {
         "box" : [
            -75.030006408691406,
            -74.99822998046875,
            -103.70832061767578,
            3.1725921630859375,
            0.0,
            0.0,
            0.0,
            3.2057380676269531,
            0.0,
            0.0,
            0.0,
            0.96495819091796875
         ]
      },
      "children" : [
         {
            "boundingVolume" : {
               "box" : [
                  -75.014259338378906,
                  -74.977951049804688,
                  -103.68878173828125,
                  3.1492843627929688,
                  0.0,
                  0.0,
                  0.0,
                  3.1869468688964844,
                  0.0,
                  0.0,
                  0.0,
                  0.94542312622070312
               ]
            },
            "content" : {
               "uri" : "h0310370.json"
            },
            "geometricError" : 0.64876657724380493
         }
      ],
      "content" : {
         "uri" : "g031037.b3dm"
      },
      "geometricError" : 1.2975331544876099
   }
}
