{
   "asset" : {
      "generator" : "osg2cesiumApp",
      "version" : "1.0"
   },
   "root" : {
      "boundingVolume" : {
         "box" : [
            -285.15496826171875,
            -207.03067016601562,
            -122.90190124511719,
            3.9453887939453125,
            0.0,
            0.0,
            0.0,
            3.9453964233398438,
            0.0,
            0.0,
            0.0,
            0.18596267700195312
         ]
      },
      "content" : {
         "uri" : "h0021213.b3dm"
      },
      "geometricError" : 0.64876216650009155
   }
}
