{
   "asset" : {
      "generator" : "osg2cesiumApp",
      "version" : "1.0"
   },
   "root" : {
      "boundingVolume" : {
         "box" : [
            -261.7171630859375,
            -214.84329223632812,
            -119.31439208984375,
            3.945404052734375,
            0.0,
            0.0,
            0.0,
            3.9453964233398438,
            0.0,
            0.0,
            0.0,
            3.3763923645019531
         ]
      },
      "content" : {
         "uri" : "h0021310.b3dm"
      },
      "geometricError" : 0.64876300096511841
   }
}
