{
   "asset" : {
      "generator" : "osg2cesiumApp",
      "version" : "1.0"
   },
   "root" : {
      "boundingVolume" : {
         "box" : [
            -300.7802734375,
            50.781898498535156,
            -117.12117004394531,
            3.9454193115234375,
            0.0,
            0.0,
            0.0,
            3.9454021453857422,
            0.0,
            0.0,
            0.0,
            3.1377334594726562
         ]
      },
      "content" : {
         "uri" : "h0131221.b3dm"
      },
      "geometricError" : 0.6487618088722229
   }
}
