{
   "asset" : {
      "generator" : "osg2cesiumApp",
      "version" : "1.0"
   },
   "root" : {
      "boundingVolume" : {
         "box" : [
            -243.42401123046875,
            82.8016357421875,
            -111.75534057617188,
            1.274322509765625,
            0.0,
            0.0,
            0.0,
            2.1598472595214844,
            0.0,
            0.0,
            0.0,
            0.69179534912109375
         ]
      },
      "content" : {
         "uri" : "h0322024.b3dm"
      },
      "geometricError" : 0.6487622857093811
   }
}
